Metadata-Version: 2.1
Name: cristianIordache
Version: 0.0.2
Summary: 2cool 4school
Author: Cristian Iordache
Author-email: cristian.iordache@ro.gt.com
Classifier: Programming Language :: Python :: 3
Classifier: Operating System :: OS Independent
